xontrib_looseene/__init__.py
xontrib_looseene/backend.py
xontrib_looseene/main.py
xontrib_looseene/ui.py
xontrib_history_looseene-1.3.0.dist-info/METADATA
xontrib_history_looseene-1.3.0.dist-info/WHEEL
xontrib_history_looseene-1.3.0.dist-info/entry_points.txt
xontrib_history_looseene-1.3.0.dist-info/top_level.txt
xontrib_history_looseene-1.3.0.dist-info/RECORD
