Metadata-Version: 2.4
Name: xontrib-history-looseene
Version: 1.3.0
Summary: fast small embed history backend
Author-email: Tsybulskyi Evhenyi <etsy2900@gmail.com>
License: MIT License
Project-URL: Homepage, https://github.com/Hammer2900/xontrib-looseene
Project-URL: Documentation, https://github.com/Hammer2900/xontrib-looseene/blob/master/README.md
Project-URL: Code, https://github.com/Hammer2900/xontrib-looseene
Project-URL: Issue tracker, https://github.com/Hammer2900/xontrib-looseene/issues
Platform: any
Classifier: Programming Language :: Python :: 3
Classifier: License :: OSI Approved :: MIT License
Classifier: Operating System :: OS Independent
Classifier: Topic :: System :: Shells
Classifier: Topic :: System :: System Shells
Classifier: Topic :: Terminals
Requires-Python: >=3.8
Requires-Dist: xonsh>=0.12.5
Provides-Extra: dev
Requires-Dist: pytest>=7.0; extra == "dev"
